apollo_tracker/__init__.py
apollo_tracker/tracker.py
apollo_tracker-0.1.4.dist-info/METADATA
apollo_tracker-0.1.4.dist-info/WHEEL
apollo_tracker-0.1.4.dist-info/top_level.txt
apollo_tracker-0.1.4.dist-info/RECORD
