Metadata-Version: 2.2
Name: apollo-tracker
Version: 0.1.4
Summary: A lightweight Flask middleware that captures and reports errors to Apollo, a centralized error tracking system.
Home-page: https://github.com/TORNIXTECH/apollo-tracker
Project-URL: Documentation, https://github.com/TORNIXTECH/apollo-tracker/wiki
Project-URL: Source Code, https://github.com/TORNIXTECH/apollo-tracker
Project-URL: Issue Tracker, https://github.com/TORNIXTECH/apollo-tracker/issues
Classifier: Programming Language :: Python :: 3
Classifier: Framework :: Flask
Classifier: License :: OSI Approved :: MIT License
Classifier: Operating System :: OS Independent
Requires-Python: >=3.6
Dynamic: classifier
Dynamic: description
Dynamic: description-content-type
Dynamic: home-page
Dynamic: project-url
Dynamic: requires-python
Dynamic: summary
